aliyunsdkehpcinstant/__init__.py
aliyunsdkehpcinstant/request/__init__.py
aliyunsdkehpcinstant/request/v20230701/AddImageRequest.py
aliyunsdkehpcinstant/request/v20230701/CreateJobRequest.py
aliyunsdkehpcinstant/request/v20230701/DeleteJobsRequest.py
aliyunsdkehpcinstant/request/v20230701/DescribeJobMetricDataRequest.py
aliyunsdkehpcinstant/request/v20230701/DescribeJobMetricLastRequest.py
aliyunsdkehpcinstant/request/v20230701/GetImageRequest.py
aliyunsdkehpcinstant/request/v20230701/GetJobRequest.py
aliyunsdkehpcinstant/request/v20230701/ListExecutorsRequest.py
aliyunsdkehpcinstant/request/v20230701/ListImagesRequest.py
aliyunsdkehpcinstant/request/v20230701/ListJobExecutorsRequest.py
aliyunsdkehpcinstant/request/v20230701/ListJobsRequest.py
aliyunsdkehpcinstant/request/v20230701/RemoveImageRequest.py
aliyunsdkehpcinstant/request/v20230701/__init__.py
aliyun_python_sdk_ehpcinstant-1.0.0.dist-info/LICENSE
aliyun_python_sdk_ehpcinstant-1.0.0.dist-info/METADATA
aliyun_python_sdk_ehpcinstant-1.0.0.dist-info/WHEEL
aliyun_python_sdk_ehpcinstant-1.0.0.dist-info/top_level.txt
aliyun_python_sdk_ehpcinstant-1.0.0.dist-info/RECORD
